{
  "analysis": {
    "marketTrend": "BTC 当前价格在91326 USDT附近震荡，1小时K线显示价格在91261.6至91699.9区间波动，短期无明显趋势。5分钟K线显示价格在91300附近窄幅整理，订单簿买卖深度接近，最优买价与卖价差仅为0.10 USDT，市场处于平衡状态。",
    "positionStatus": "当前无持仓，账户处于空仓状态，可灵活选择开仓时机。",
    "riskAssessment": "账户总余额994.70 USDT，可用保证金充足，风险等级LOW，保证金使用率0%，无爆仓风险。"
  },
  "signal": {
    "action": "HOLD",
    "confidence": "MEDIUM",
    "reasoning": "市场当前处于震荡格局，缺乏明确的方向性信号。订单簿深度显示多空力量均衡，且关键支撑阻力位（91000-91600）尚未突破，建议暂时观望等待趋势确认。"
  },
  "execution": {
    "hasOrder": false,
    "orders": []
  },
  "riskWarning": "震荡行情中频繁交易可能增加磨损成本，需等待明确突破信号再操作。"
}